LICENSE
MANIFEST.in
README.rst
setup.py
django_glrm.egg-info/PKG-INFO
django_glrm.egg-info/SOURCES.txt
django_glrm.egg-info/dependency_links.txt
django_glrm.egg-info/top_level.txt
docs/MAKEFILE
docs/code.rst
docs/conf.py
docs/index.rst
docs/readme.rst
global_login_required/__init__.py
global_login_required/tests.py
global_login_required/urls.py
global_login_required/views.py