Metadata-Version: 1.1
Name: django-glrm
Version: 1.1.3
Summary: A Django middleware that make all views and URLs login required.
Home-page: UNKNOWN
Author: M.A. Heshmatkhah
Author-email: maheshmatkhah.prg@gmail.com
License: Apache Software License
Project-URL: Source, https://github.com/MA-Heshmatkhah/django-glrm/
Project-URL: Documentation, http://django-glrm.readthedocs.io/
Project-URL: Tracker, https://github.com/MA-Heshmatkhah/django-glrm/issues
Platform: UNKNOWN
Classifier: Environment :: Web Environment
Classifier: Framework :: Django
Classifier: Framework :: Django :: 1.10
Classifier: Framework :: Django :: 1.11
Classifier: Framework :: Django :: 2.0
Classifier: Intended Audience :: Developers
Classifier: License :: OSI Approved :: Apache Software License
Classifier: Operating System :: OS Independent
Classifier: Programming Language :: Python
Classifier: Programming Language :: Python :: 3.5
Classifier: Programming Language :: Python :: 3.6
Classifier: Programming Language :: Python :: 3.7
Classifier: Topic :: Internet :: WWW/HTTP
Classifier: Topic :: Internet :: WWW/HTTP :: Dynamic Content
